kebechet/__init__.py
kebechet/cli.py
kebechet/config.py
kebechet/exception.py
kebechet/payload_parser.py
kebechet/services.py
kebechet/utils.py
kebechet/managers/__init__.py
kebechet/managers/manager.py
kebechet/managers/info/__init__.py
kebechet/managers/info/info.py
kebechet/managers/info/messages.py
kebechet/managers/pipfile_requirements/__init__.py
kebechet/managers/pipfile_requirements/pipfile_requirements.py
kebechet/managers/thoth_advise/__init__.py
kebechet/managers/thoth_advise/thoth_advise.py
kebechet/managers/thoth_provenance/__init__.py
kebechet/managers/thoth_provenance/thoth_provenance.py
kebechet/managers/update/__init__.py
kebechet/managers/update/messages.py
kebechet/managers/update/update.py
kebechet/managers/version/__init__.py
kebechet/managers/version/version.py
kebechet/managers/version/version_test.py
kebechet-1.1.1.dist-info/METADATA
kebechet-1.1.1.dist-info/RECORD
kebechet-1.1.1.dist-info/WHEEL
kebechet-1.1.1.dist-info/entry_points.txt
kebechet-1.1.1.dist-info/top_level.txt
