Metadata-Version: 2.1
Name: kebechet
Version: 1.1.1
Summary: Keep your dependencies in your projects fresh and up2date
Home-page: UNKNOWN
Author: Fridolin Pokorny
Author-email: fridolin@redhat.com
License: GPLv3+
Platform: UNKNOWN
Requires-Dist: click
Requires-Dist: daiquiri
Requires-Dist: pipenv (==2018.11.26)
Requires-Dist: toml
Requires-Dist: delegator.py
Requires-Dist: pyyaml
Requires-Dist: gitpython (>=3.1.0)
Requires-Dist: requests
Requires-Dist: semver
Requires-Dist: sentry-sdk
Requires-Dist: thoth-common
Requires-Dist: thoth-sourcemanagement
Requires-Dist: thoth-glyph
